CHANGES.txt
LICENSE.txt
MANIFEST.in
README.md
requirements.txt
setup.cfg
setup.py
PyQt_Fit.egg-info/PKG-INFO
PyQt_Fit.egg-info/SOURCES.txt
PyQt_Fit.egg-info/dependency_links.txt
PyQt_Fit.egg-info/requires.txt
PyQt_Fit.egg-info/top_level.txt
bin/pyqt_fit1d.py
docs/GUI_tut.rst
docs/KDE_tut.rst
docs/Makefile
docs/NonParam_tut.rst
docs/Param_tut.rst
docs/conf.py
docs/index.rst
docs/intro.rst
docs/mod_bootstrap.rst
docs/mod_curve_fitting.rst
docs/mod_kde.rst
docs/mod_kde_methods.rst
docs/mod_kernels.rst
docs/mod_nonparam_regression.rst
docs/mod_npr_methods.rst
docs/mod_plot_fit.rst
docs/mod_utils.rst
docs/modules.rst
pyqt_fit/__init__.py
pyqt_fit/_kde.pyx
pyqt_fit/_kernels.pyx
pyqt_fit/_kernels_py.py
pyqt_fit/binning.py
pyqt_fit/bootstrap.py
pyqt_fit/bootstrap_workers.py
pyqt_fit/compat.py
pyqt_fit/curve_fitting.py
pyqt_fit/cy_binning.pyx
pyqt_fit/cy_local_linear.pyx
pyqt_fit/cyth.py
pyqt_fit/kde.py
pyqt_fit/kde_bandwidth.py
pyqt_fit/kde_methods.py
pyqt_fit/kernel_smoothing.py
pyqt_fit/kernels.py
pyqt_fit/loader.py
pyqt_fit/math.pxd
pyqt_fit/nonparam_regression.py
pyqt_fit/npr_methods.py
pyqt_fit/plot_fit.py
pyqt_fit/py_binning.py
pyqt_fit/py_local_linear.py
pyqt_fit/pyqt_fit1d.py
pyqt_fit/qt_fit.ui
pyqt_fit/sharedmem.py
pyqt_fit/utils.py
pyqt_fit/version.txt
pyqt_fit/functions/__init__.py
pyqt_fit/functions/simple.py
pyqt_fit/residuals/__init__.py
pyqt_fit/residuals/simple.py
pyqt_fit/test/__init__.py
pyqt_fit/test/kde_utils.py
pyqt_fit/test/test_bootstrap.py
pyqt_fit/test/test_bootstrap_workers.py
pyqt_fit/test/test_cdf.py
pyqt_fit/test/test_curve_fitting.py
pyqt_fit/test/test_cyth.py
pyqt_fit/test/test_kde.py
pyqt_fit/test/test_kernels.py
pyqt_fit/test/test_loader.py
pyqt_fit/test/test_nonparam_regression.py
pyqt_fit/test/test_plot_fit.py
pyqt_fit/test/test_pyqt_fit1d.py
pyqt_fit/test/test_sharedmem.py
pyqt_fit/test/test_utils.py