Metadata-Version: 2.1
Name: PyQt-Fit
Version: 1.4.0
Summary: Parametric and non-parametric regression, with plotting and testing methods.
Home-page: https://github.com/PierreBdR/PyQt-fit
Author: Pierre Barbier de Reuille
Author-email: pierre.barbierdereuille@gmail.com
License: LICENSE.txt
Download-URL: https://github.com/PierreBdR/PyQt-fit/archive/v_1_4_0.tar.gz
Platform: Linux
Platform: Windows
Platform: MacOS
Classifier: Development Status :: 4 - Beta
Classifier: Environment :: X11 Applications :: Qt
Classifier: Intended Audience :: Science/Research
Classifier: License :: OSI Approved :: GNU General Public License v3 or later (GPLv3+)
Classifier: Natural Language :: English
Classifier: Operating System :: MacOS :: MacOS X
Classifier: Operating System :: Microsoft :: Windows
Classifier: Operating System :: POSIX :: Linux
Classifier: Programming Language :: Python :: 3.6
Classifier: Topic :: Scientific/Engineering :: Mathematics
Classifier: Topic :: Scientific/Engineering :: Visualization
Provides-Extra: Cython
